spatial_domain/__init__.py
spatial_domain/anomaly.py
vcosmos-1.1.0.dist-info/LICENSE.txt
vcosmos-1.1.0.dist-info/METADATA
vcosmos-1.1.0.dist-info/WHEEL
vcosmos-1.1.0.dist-info/top_level.txt
vcosmos-1.1.0.dist-info/RECORD
