Metadata-Version: 2.1
Name: vcosmos
Version: 1.1.0
Summary: This package implements a 3D projection-based outlier detection algorithm using median-derived distance thresholds.
Home-page: https://github.com/KarthikDevalla/vcosmos.git
Author: Karthik Devalla
Author-email: ihatecoding666@gmail.com
Classifier: Programming Language :: Python :: 3
Classifier: License :: OSI Approved :: MIT License
Classifier: Operating System :: OS Independent
Requires-Python: >=3.10
License-File: LICENSE.txt
